{
    "maxerr": 50,
    "node": true,
    "browser": true,
    "esnext": true,
    "bitwise": true,
    "curly": true,
    "eqeqeq": true,
    "latedef": true,
    "newcap": true,
    "noempty": true,
    "noarg": true,
    "undef": true,
    "unused": true,
    "strict": true,
    "trailing": true,
    "laxcomma": true,
    "maxparams" : 3,
    "maxdepth" : 3,
    "globals": {
        "expect": false,
        "it": false,
        "element": false,
        "describe": false,
        "window": false,
        "document": false,
        "inject": false,
        "module": false,
        "_": false,
        "beforeEach": false,
        "browser": false
    }
}
